CONTRIBUTING.md
LICENSE
MANIFEST.in
Makefile
README.md
pyproject.toml
setup.py
gsheetquery/__init__.py
gsheetquery/_version.py
gsheetquery/client.py
gsheetquery/collection.py
gsheetquery/database.py
gsheetquery/utils.py
gsheetquery.egg-info/PKG-INFO
gsheetquery.egg-info/SOURCES.txt
gsheetquery.egg-info/dependency_links.txt
gsheetquery.egg-info/requires.txt
gsheetquery.egg-info/top_level.txt
gsheetquery/tests/client_test.py
gsheetquery/tests/collection_test.py
gsheetquery/tests/database_test.py
gsheetquery/tests/integration_test.py
gsheetquery/tests/utils_test.py