Metadata-Version: 2.1
Name: gsheetquery
Version: 0.0.3
Summary: A Google Sheets ORM and Query Builder
Author-email: Noah Czelusta <swimninja247@gmail.com>
License: MIT License
Project-URL: repository, https://github.com/swimninja247/gsheetquery
Classifier: Development Status :: 2 - Pre-Alpha
Classifier: Programming Language :: Python :: Implementation :: CPython
Classifier: Programming Language :: Python :: Implementation :: PyPy
Classifier: Programming Language :: Python :: 3
Classifier: Programming Language :: Python :: 3.7
Classifier: Programming Language :: Python :: 3.8
Classifier: Programming Language :: Python :: 3.9
Classifier: Programming Language :: Python :: 3.10
Classifier: Programming Language :: Python :: 3.11
Requires-Python: >=3.8
Provides-Extra: develop
License-File: LICENSE
